easydetabase.py
easydetabase-1.0.11.dist-info/LICENSE
easydetabase-1.0.11.dist-info/METADATA
easydetabase-1.0.11.dist-info/WHEEL
easydetabase-1.0.11.dist-info/top_level.txt
easydetabase-1.0.11.dist-info/RECORD
