Metadata-Version: 2.1
Name: easydetabase
Version: 1.0.11
Summary: easydetabase interact with deta base service in easy way
Home-page: https://github.com/EmaGianna/easy-detabase
Author: Emanuel Giannattasio
Author-email: emanuel.giannattasio@gmail.com
Requires-Python: >=3.8
License-File: LICENSE
Requires-Dist: deta
Requires-Dist: pandas
